topsis/__init__.py
topsis/topsis.py
topsis_Pranav_102216023-0.1.1.dist-info/METADATA
topsis_Pranav_102216023-0.1.1.dist-info/WHEEL
topsis_Pranav_102216023-0.1.1.dist-info/entry_points.txt
topsis_Pranav_102216023-0.1.1.dist-info/top_level.txt
topsis_Pranav_102216023-0.1.1.dist-info/RECORD
