Metadata-Version: 2.1
Name: topsis-Pranav-102216023
Version: 0.1.1
Summary: A Python package for performing TOPSIS analysis.
Home-page: https://github.com/Pranav07Duggal/UCS654/blob/main/102216023.py
Author: Pranav Duggal
Classifier: Programming Language :: Python :: 3
Classifier: License :: OSI Approved :: MIT License
Classifier: Operating System :: OS Independent
Requires-Python: >=3.6
Requires-Dist: numpy
Requires-Dist: pandas
